[
    {
        "name": "Adilova Diyora",
        "program": "CSE",
        "level": "2",
        "email": "d.adilova@student.inha.uz",
        "phone": "+998974348858",
        "id": "U2210020",
        "section": "2"
    },
    {
        "name": "Inomjonov Javokhirbek",
        "program": "CSE",
        "level": "2",
        "email": "j.inomjonov@student.inha.uz",
        "phone": "+998974430132",
        "id": "U2210086",
        "section": "3"
    },
    {
        "name": "Aydinov Elbek",
        "program": "CSE",
        "level": "2",
        "email": "e.aydinov@student.inha.uz",
        "phone": "+998973208164",
        "id": "U2210039",
        "section": "3"
    },
    {
        "name": "Bazarov Sarvar",
        "program": "ICE",
        "level": "2",
        "email": "s.bazarov@student.inha.uz",
        "phone": "+998977244429",
        "id": "U2210050",
        "section": "1"
    },
    {
        "name": "Abdimannabov Sardor",
        "program": "CSE",
        "level": "2",
        "email": "s.abdimannabov@student.inha.uz",
        "phone": "+998931857667",
        "id": "U2210002",
        "section": "2"
    },
    {
        "name": "Makhmudov Sardor",
        "program": "ICE",
        "level": "2",
        "email": "s.makhmudov@student.inha.uz",
        "phone": "+998990202235",
        "id": "U2210131",
        "section": "1"
    },
    {
        "name": "Akramov Rashod",
        "program": "ICE",
        "level": "2",
        "email": "r.akramov@student.inha.uz",
        "phone": "+998909162868",
        "id": "U2210025",
        "section": "1"
    },
    {
        "name": "Saydaxmedov Sayidaxror",
        "program": "ICE",
        "level": "2",
        "email": "s.saydaxmedov@student.inha.uz",
        "phone": "+998946991483",
        "id": "U2210206",
        "section": "1"
    },
    {
        "name": "Rakhmanova Kamila",
        "program": "CSE",
        "level": "2",
        "email": "k.rakhmanova@student.inha.uz",
        "phone": "+998935647453",
        "id": "U2210184",
        "section": "4"
    },
    {
        "name": "Maxkamov Abbos",
        "program": "CSE",
        "level": "2",
        "email": "a.maxmakov@student.inha.uz",
        "phone": "+998909645070",
        "id": "U2210138",
        "section": "4"
    },
    {
        "name": "Begmamatova Muattar",
        "program": "CSE",
        "level": "2",
        "email": "m.begmamatova@student.inha.uz",
        "phone": "+998934630410",
        "id": "U2210051",
        "section": "2"
    },
    {
        "name": "Shovkatjon Komilov",
        "program": "CSE",
        "level": "2",
        "email": "s.komilov3@student.inha.uz",
        "phone": "+998990515405",
        "id": "U2210122",
        "section": "3"
    },
    {
        "name": "Rofiev Mukhammadali",
        "program": "CSE",
        "level": "2",
        "email": "m.rofiev@student.inha.uz",
        "phone": "+998974875565",
        "id": "U2010228",
        "section": "3"
    },
    {
        "name": "Adam Saidov",
        "program": "CSE",
        "level": "2",
        "email": "a.saidov@student.inha.uz",
        "phone": "+998938555521",
        "id": "U2010240",
        "section": "3"
    },
    {
        "name": "Nodirakhon Abdullaeva",
        "program": "CSE",
        "level": "2",
        "email": "n.abdullaeva@student.inha.uz",
        "phone": "+998884752020",
        "id": "U2210008",
        "section": "2"
    },
    {
        "name": "Ilyosov Doniyor",
        "program": "CSE",
        "level": "2",
        "email": "d.ilyosov@student.inha.uz",
        "phone": "+998990252005",
        "id": "U2210085",
        "section": "2"
    },
    {
        "name": "Tulkunov Xasan",
        "program": "CSE",
        "level": "2",
        "email": "x.tulkunov@student.inha.uz",
        "phone": "+998908944442",
        "id": "U2210229",
        "section": "4"
    },
    {
        "name": "Jorayev Saidakbar",
        "program": "CSE",
        "level": "2",
        "email": "s.jo'rayev@student.inha.uz",
        "phone": "+998909262968",
        "id": "U2210096",
        "section": "4"
    },
    {
        "name": "Xalibayev Iskander",
        "program": "CSE",
        "level": "2",
        "email": "i.xalibayev@student.inha.uz",
        "phone": "+998936969228",
        "id": "U2210249",
        "section": "4"
    },
    {
        "name": "Xatamov Javohirbek",
        "program": "CSE",
        "level": "2",
        "email": "j.xatamov@student.inha.uz",
        "phone": "+998902075639",
        "id": "U2210251",
        "section": "3"
    },
    {
        "name": "Musulmonov Abror",
        "program": "CSE",
        "level": "2",
        "email": "a.musulmonov@student.inha.uz",
        "phone": "+998934436004",
        "id": "U2210278",
        "section": "4"
    },
    {
        "name": "Xonboboyev Abdulxafizxon",
        "program": "CSE",
        "level": "2",
        "email": "a.xonboboyev@student.inha.uz",
        "phone": "+998907885003",
        "id": "U2210253",
        "section": "3"
    },
    {
        "name": "Saidova Jasmina",
        "program": "CSE",
        "level": "2",
        "email": "j.saidova@student.inha.uz",
        "phone": "+998974104024",
        "id": "U2210203",
        "section": "3"
    },
    {
        "name": "Abdurakhmanov Bobokhon",
        "program": "CSE",
        "level": "2",
        "email": "b.abdurakhmanov@student.inha.uz",
        "phone": "+998903580148",
        "id": "U2210015",
        "section": "3"
    },
    {
        "name": "Sodikov Akmaljon",
        "program": "CSE",
        "level": "2",
        "email": "a.sodikov3@student.inha.uz",
        "phone": "+998900941289",
        "id": "U2210214",
        "section": "3"
    },
    {
        "name": "Mansurov Diyorbek",
        "program": "CSE",
        "level": "2",
        "email": "d.mansurov@student.inha.uz",
        "phone": "+998908297743",
        "id": "U2210134",
        "section": "3"
    },
    {
        "name": "Kim Aleksandr",
        "program": "ICE",
        "level": "2",
        "email": "a.kim7@student.inha.uz",
        "phone": "+998915395545",
        "id": "U2210112",
        "section": "1"
    },
    {
        "name": "Tselishcheva Milana",
        "program": "CSE",
        "level": "2",
        "email": "m.tselishcheva@student.inha.uz",
        "phone": "+998909555369",
        "id": "U2210227",
        "section": "3"
    },
    {
        "name": "Vosiljonov Mirvokhid",
        "program": "CSE",
        "level": "2",
        "email": "m.vosiljonov@student.inha.uz",
        "phone": "+998930084603",
        "id": "U2210246",
        "section": "4"
    },
    {
        "name": "Kim Denis",
        "program": "ICE",
        "level": "2",
        "email": "d.kim5@student.inha.uz",
        "phone": "+998339154327",
        "id": "U2210116",
        "section": "1"
    },
    {
        "name": "Rakhmanov Azizjon",
        "program": "ICE",
        "level": "2",
        "email": "a.rakhmanov@student.inha.uz",
        "phone": "+998330019896",
        "id": "U2210183",
        "section": "1"
    },
    {
        "name": "Nurmuhammad Nuriddinov",
        "program": "ICE",
        "level": "2",
        "email": "n.nuriddinov@student.inha.uz",
        "phone": "+998996640849",
        "id": "U2210167",
        "section": "1"
    },
    {
        "name": "Tayirova Norjonoy",
        "program": "CSE",
        "level": "2",
        "email": "n.tayirova@student.inha.uz",
        "phone": "+998934347628",
        "id": "U2210219",
        "section": "3"
    },
    {
        "name": "Sultanov Amal",
        "program": "CSE",
        "level": "2",
        "email": "a.sultanov2@student.inha.uz",
        "phone": "+998935960748",
        "id": "U2210217",
        "section": "4"
    },
    {
        "name": "Muslima Okiljonova",
        "program": "ICE",
        "level": "2",
        "email": "m.okiljonova@student.inha.uz",
        "phone": "+998940263373",
        "id": "U2210171",
        "section": "1"
    },
    {
        "name": "Sharipova Nargiza",
        "program": "CSE",
        "level": "2",
        "email": "n.sharipova@student.inha.uz",
        "phone": "+998907116702",
        "id": "U2210207",
        "section": "3"
    },
    {
        "name": "Khegay Viktor",
        "program": "CSE",
        "level": "2",
        "email": "v.khegay@student.inha.uz",
        "phone": "+998900335569",
        "id": "U2210108",
        "section": "3"
    },
    {
        "name": "Turayev Abdugafur",
        "program": "CSE",
        "level": "2",
        "email": "a.turayev@student.inha.uz",
        "phone": "+998998689445",
        "id": "U2210231",
        "section": "4"
    },
    {
        "name": "Samokhin Kirill",
        "program": "CSE",
        "level": "2",
        "email": "k.samokhin@student.inha.uz",
        "phone": "+998909391435",
        "id": "U2210204",
        "section": "3"
    },
    {
        "name": "Ilkhomov Farrukh",
        "program": "ICE",
        "level": "2",
        "email": "f.ilkhomov@student.inha.uz",
        "phone": "+998903279011",
        "id": "U2210084",
        "section": "1"
    },
    {
        "name": "Maxmudov Komron",
        "program": "ICE",
        "level": "2",
        "email": "kamranmaxmudov9@gmail.com",
        "phone": "+998915422734",
        "id": "U2210141",
        "section": "1"
    },
    {
        "name": "Kim Svetlana",
        "program": "ICE",
        "level": "2",
        "email": "cydnsa.ks@gmail.com",
        "phone": "+998998661678",
        "id": "U2210117",
        "section": "1"
    },
    {
        "name": "Urazbaev Nurmukhamed",
        "program": "CSE",
        "level": "2",
        "email": "n.urazbaev@student.inha.uz",
        "phone": "+998930025154",
        "id": "U2210239",
        "section": "4"
    },
    {
        "name": "Ilchikayev Amir",
        "program": "ICE",
        "level": "2",
        "email": "a.ilchikayev@student.inha.uz",
        "phone": "+998909956027",
        "id": "U2210083",
        "section": "1"
    },
    {
        "name": "Ablyayeva Susanna",
        "program": "CSE",
        "level": "2",
        "email": "s.ablyayeva@student.inha.uz",
        "phone": "+998911375550",
        "id": "U2210018",
        "section": "2"
    },
    {
        "name": "Zeboxon Abdullayeva",
        "program": "CSE",
        "level": "2",
        "email": "z.abdullayeva@student.inha.uz",
        "phone": "+998901234567",
        "id": "U2210011",
        "section": "4"
    },
    {
        "name": "Akhrarova Munisa",
        "program": "CSE",
        "level": "2",
        "email": "m.akhrarova@student.inha.uz",
        "phone": "+998935820811",
        "id": "U2210024",
        "section": "2"
    },
    {
        "name": "Uyg\u2019un Tursunov",
        "program": "CSE",
        "level": "2",
        "email": "u.tursunov@student.inha.uz",
        "phone": "+998912445105",
        "id": "U2210234",
        "section": "4"
    },
    {
        "name": "Islomov Kamronbek",
        "program": "CSE",
        "level": "2",
        "email": "k.islomov@student.inha.uz",
        "phone": "+998902965156",
        "id": "U2210279",
        "section": "4"
    },
    {
        "name": "Javohir Rasuljanov",
        "program": "CSE",
        "level": "2",
        "email": "j.rasuljonov@student.inha.uz",
        "phone": "+998998652057",
        "id": "U2210187",
        "section": "4"
    },
    {
        "name": "Maxsudov Mirshod",
        "program": "ICE",
        "level": "2",
        "email": "mirshodmakhsudov@gmail.com",
        "phone": "+998334009697",
        "id": "U2210142",
        "section": "1"
    },
    {
        "name": "Anvarov Aslbek",
        "program": "CSE",
        "level": "2",
        "email": "a.anvarov2@student.inha.uz",
        "phone": "+998901883599",
        "id": "U2210031",
        "section": "2"
    },
    {
        "name": "Arslonov Zokirjon",
        "program": "CSE",
        "level": "2",
        "email": "z.arslonov@student.inha.uz",
        "phone": "+998996418060",
        "id": "U2210033",
        "section": "2"
    },
    {
        "name": "Alokhujaev Akbarkhuja",
        "program": "CSE",
        "level": "2",
        "email": "a.alokhujaev@student.inha.uz",
        "phone": "+998990493336",
        "id": "U2210028",
        "section": "3"
    },
    {
        "name": "To'ychiyeva Nozima",
        "program": "CSE",
        "level": "2",
        "email": "n.to'ychiyeva@student.inha.uz",
        "phone": "+998998799028",
        "id": "U2210226",
        "section": "3"
    },
    {
        "name": "Ergashev Muhammadaziz",
        "program": "ICE",
        "level": "2",
        "email": "m.ergashev@student.inha.uz",
        "phone": "+998974212004",
        "id": "U2210064",
        "section": "1"
    },
    {
        "name": "Dyugay Vladimir",
        "program": "ICE",
        "level": "2",
        "email": "v.dyugay@student.inha.uz",
        "phone": "+998901342108",
        "id": "U2210061",
        "section": "1"
    },
    {
        "name": "Ibroilov Izzatulla",
        "program": "ICE",
        "level": "2",
        "email": "iibroilov@gmail.com",
        "phone": "+998908225808",
        "id": "U2210082",
        "section": "1"
    },
    {
        "name": "Jo\u2019raqulov Anvarjon",
        "program": "ICE",
        "level": "2",
        "email": "anvarjonjurakulov@gmail.com",
        "phone": "+998999999056",
        "id": "U2210094",
        "section": "1"
    },
    {
        "name": "Azimov Abdulla",
        "program": "ICE",
        "level": "2",
        "email": "flash2003.lol@gmail.com",
        "phone": "+998935069556",
        "id": "U2210041",
        "section": "1"
    },
    {
        "name": "Isakov Sarvar",
        "program": "ICE",
        "level": "2",
        "email": "s.isakov@gmail.com",
        "phone": "+998973333009",
        "id": "U2210087",
        "section": "1"
    },
    {
        "name": "Diyorkho\u2019ja Fayzullayev",
        "program": "ICE",
        "level": "2",
        "email": "f3249987@gmail.com",
        "phone": "+998998552860",
        "id": "U2210072",
        "section": "1"
    },
    {
        "name": "Zokirov Habibullo",
        "program": "CSE",
        "level": "2",
        "email": "h.zokirov@student.inha.uz",
        "phone": "+998974400335",
        "id": "U2210266",
        "section": "4"
    },
    {
        "name": "Muhammadali Koraev",
        "program": "ICE",
        "level": "2",
        "email": "m.koraev@student.inha.uz",
        "phone": "+998999202141",
        "id": "U2210123",
        "section": "1"
    },
    {
        "name": "Rasulov Abdulaziz",
        "program": "CSE",
        "level": "2",
        "email": "a.rasulov@student.inha.uz",
        "phone": "+998994303858",
        "id": "U2110237",
        "section": "4"
    },
    {
        "name": "Abdurakhimov Fuzaylkhon",
        "program": "CSE",
        "level": "2",
        "email": "f.abdurakhimov@student.inha.uz",
        "phone": "+998909460014",
        "id": "U2210013",
        "section": "2"
    },
    {
        "name": "Usmanov Dilshod",
        "program": "CSE",
        "level": "2",
        "email": "d.usmanov2@student.inha.uz",
        "phone": "+998930010254",
        "id": "U2210241",
        "section": "4"
    },
    {
        "name": "Tursunov Asiliddin",
        "program": "CSE",
        "level": "2",
        "email": "a.tursunov4@student.inha.uz",
        "phone": "+998903737713",
        "id": "U2210233",
        "section": "4"
    },
    {
        "name": "Makhmudov Imronbek",
        "program": "CSE",
        "level": "2",
        "email": "i.makhmudov@student.inha.uz",
        "phone": "+998771779775",
        "id": "U2210130",
        "section": "4"
    }
]